virtualeditor/__init__.py
virtualeditor-0.0.1.dist-info/LICENSE
virtualeditor-0.0.1.dist-info/METADATA
virtualeditor-0.0.1.dist-info/WHEEL
virtualeditor-0.0.1.dist-info/top_level.txt
virtualeditor-0.0.1.dist-info/RECORD
