Metadata-Version: 2.1
Name: virtualeditor
Version: 0.0.1
Summary: A virtual editor to make coding videos.
Home-page: https://github.com/sarmadgulzar/virtualeditor
Author: Sarmad Gulzar
Author-email: sarmadgulzar@hotmail.com
License: UNKNOWN
Platform: UNKNOWN
Classifier: Programming Language :: Python :: 3
Classifier: License :: OSI Approved :: MIT License
Classifier: Operating System :: OS Independent
Requires-Python: >=3.6
